mcp_server_memos/__init__.py
mcp_server_memos/__main__.py
mcp_server_memos/config.py
mcp_server_memos/server.py
mcp_server_memos/proto_gen/__init__.py
mcp_server_memos/proto_gen/google/__init__.py
mcp_server_memos/proto_gen/google/api/__init__.py
mcp_server_memos/proto_gen/memos/__init__.py
mcp_server_memos/proto_gen/memos/api/__init__.py
mcp_server_memos/proto_gen/memos/api/v1/__init__.py
mseep_mcp_server_memos-0.1.19.dist-info/licenses/LICENSE
mseep_mcp_server_memos-0.1.19.dist-info/METADATA
mseep_mcp_server_memos-0.1.19.dist-info/WHEEL
mseep_mcp_server_memos-0.1.19.dist-info/entry_points.txt
mseep_mcp_server_memos-0.1.19.dist-info/top_level.txt
mseep_mcp_server_memos-0.1.19.dist-info/RECORD
