Metadata-Version: 2.4
Name: mseep-mcp-server-memos
Version: 0.1.19
Summary: Add your description here
Author-email: mseep <support@skydeck.ai>
License: MIT License
Project-URL: Repository, https://github.com/RyoJerryYu/mcp-server-memos-py
Classifier: Development Status :: 3 - Alpha
Classifier: Intended Audience :: Developers
Classifier: License :: OSI Approved :: MIT License
Classifier: Programming Language :: Python :: 3
Classifier: Programming Language :: Python :: 3.12
Classifier: Programming Language :: Python :: 3.13
Requires-Python: >=3.12
License-File: LICENSE
Requires-Dist: mcp>=1.1.0
Requires-Dist: betterproto[compiler]>=2.0.0b6
Requires-Dist: grpclib>=0.4.7
Requires-Dist: pydantic>=2.10.3
Dynamic: license-file
